phi/__init__.py
phi/constants.py
phi/py.typed
phi/agent/__init__.py
phi/agent/agent.py
phi/agent/duckdb.py
phi/agent/python.py
phi/agent/session.py
phi/api/__init__.py
phi/api/agent.py
phi/api/api.py
phi/api/assistant.py
phi/api/playground.py
phi/api/prompt.py
phi/api/routes.py
phi/api/team.py
phi/api/user.py
phi/api/workspace.py
phi/api/schemas/__init__.py
phi/api/schemas/agent.py
phi/api/schemas/ai.py
phi/api/schemas/assistant.py
phi/api/schemas/monitor.py
phi/api/schemas/playground.py
phi/api/schemas/prompt.py
phi/api/schemas/response.py
phi/api/schemas/team.py
phi/api/schemas/user.py
phi/api/schemas/workspace.py
phi/app/__init__.py
phi/app/base.py
phi/app/context.py
phi/app/db_app.py
phi/app/group.py
phi/assistant/__init__.py
phi/assistant/assistant.py
phi/assistant/duckdb.py
phi/assistant/python.py
phi/assistant/run.py
phi/assistant/openai/__init__.py
phi/assistant/openai/assistant.py
phi/assistant/openai/exceptions.py
phi/assistant/openai/message.py
phi/assistant/openai/row.py
phi/assistant/openai/run.py
phi/assistant/openai/thread.py
phi/assistant/openai/tool.py
phi/assistant/openai/file/__init__.py
phi/assistant/openai/file/file.py
phi/assistant/openai/file/local.py
phi/assistant/openai/file/url.py
phi/aws/__init__.py
phi/aws/api_client.py
phi/aws/resources.py
phi/aws/app/__init__.py
phi/aws/app/base.py
phi/aws/app/context.py
phi/aws/app/django/__init__.py
phi/aws/app/django/django.py
phi/aws/app/fastapi/__init__.py
phi/aws/app/fastapi/fastapi.py
phi/aws/app/jupyter/__init__.py
phi/aws/app/jupyter/jupyter.py
phi/aws/app/qdrant/__init__.py
phi/aws/app/qdrant/qdrant.py
phi/aws/app/streamlit/__init__.py
phi/aws/app/streamlit/streamlit.py
phi/aws/resource/__init__.py
phi/aws/resource/base.py
phi/aws/resource/reference.py
phi/aws/resource/types.py
phi/aws/resource/acm/__init__.py
phi/aws/resource/acm/certificate.py
phi/aws/resource/cloudformation/__init__.py
phi/aws/resource/cloudformation/stack.py
phi/aws/resource/ec2/__init__.py
phidata-2.7.4.dist-info/LICENSE
phidata-2.7.4.dist-info/METADATA
phidata-2.7.4.dist-info/WHEEL
phidata-2.7.4.dist-info/entry_points.txt
phidata-2.7.4.dist-info/top_level.txt
phidata-2.7.4.dist-info/RECORD
