Metadata-Version: 2.1
Name: phidata
Version: 2.7.4
Summary: Build multi-modal Agents with memory, knowledge and tools.
Author-email: Ashpreet Bedi <ashpreet@phidata.com>
Project-URL: homepage, https://phidata.com
Project-URL: documentation, https://docs.phidata.com
Requires-Python: >=3.7
License-File: LICENSE
Requires-Dist: gitpython
Requires-Dist: httpx
Requires-Dist: pydantic
Requires-Dist: pydantic-settings
Requires-Dist: python-dotenv
Requires-Dist: pyyaml
Requires-Dist: rich
Requires-Dist: tomli
Requires-Dist: typer
Requires-Dist: typing-extensions
Provides-Extra: dev
Requires-Dist: mypy; extra == "dev"
Requires-Dist: pytest; extra == "dev"
Requires-Dist: ruff; extra == "dev"
Requires-Dist: types-pyyaml; extra == "dev"
Requires-Dist: timeout-decorator; extra == "dev"
Provides-Extra: docker
Requires-Dist: docker; extra == "docker"
Provides-Extra: aws
Requires-Dist: docker; extra == "aws"
Requires-Dist: boto3; extra == "aws"
Provides-Extra: k8s
Requires-Dist: docker; extra == "k8s"
Requires-Dist: kubernetes; extra == "k8s"
Provides-Extra: server
Requires-Dist: fastapi; extra == "server"
Requires-Dist: uvicorn; extra == "server"
Provides-Extra: all
Requires-Dist: mypy; extra == "all"
Requires-Dist: pytest; extra == "all"
Requires-Dist: ruff; extra == "all"
Requires-Dist: types-pyyaml; extra == "all"
Requires-Dist: docker; extra == "all"
Requires-Dist: boto3; extra == "all"
Requires-Dist: kubernetes; extra == "all"
Requires-Dist: fastapi; extra == "all"
Requires-Dist: uvicorn; extra == "all"
